paal/__init__.py
paal-0.0.0.dist-info/METADATA
paal-0.0.0.dist-info/WHEEL
paal-0.0.0.dist-info/top_level.txt
paal-0.0.0.dist-info/RECORD
