Metadata-Version: 2.4
Name: paal
Version: 0.0.0
Summary: paal
Author: wrmsr
License-Expression: BSD-3-Clause
Project-URL: source, https://github.com/wrmsr/paal
Classifier: Development Status :: 2 - Pre-Alpha
Classifier: Intended Audience :: Developers
Classifier: Operating System :: OS Independent
Classifier: Operating System :: POSIX
Classifier: Programming Language :: Python :: 3
Classifier: Programming Language :: Python :: 3.13
Requires-Python: >=3.13
